acumos_dcae_model_runner/__init__.py
acumos_dcae_model_runner/runner.py
acumos_dcae_model_runner-0.1.3.dist-info/DESCRIPTION.rst
acumos_dcae_model_runner-0.1.3.dist-info/METADATA
acumos_dcae_model_runner-0.1.3.dist-info/RECORD
acumos_dcae_model_runner-0.1.3.dist-info/WHEEL
acumos_dcae_model_runner-0.1.3.dist-info/entry_points.txt
acumos_dcae_model_runner-0.1.3.dist-info/metadata.json
acumos_dcae_model_runner-0.1.3.dist-info/top_level.txt
