Metadata-Version: 2.0
Name: acumos-dcae-model-runner
Version: 0.1.3
Summary: Provides an Acumos model runner for DCAE
Home-page: https://gerrit.acumos.org/r/gitweb?p=python-dcae-model-runner.git
Author: Paul Triantafyllou
Author-email: trianta@research.att.com
License: Apache License 2.0
Keywords: acumos dcae
Platform: UNKNOWN
Classifier: Development Status :: 4 - Beta
Classifier: Intended Audience :: Developers
Classifier: Programming Language :: Python :: 3
Classifier: Programming Language :: Python :: 3.5
Classifier: Programming Language :: Python :: 3.6
Classifier: License :: OSI Approved :: Apache Software License
Requires-Python: >=3.5
Requires-Dist: acumos (>=0.5.0)
Requires-Dist: dcaeapplib (<2.0.0)
